bert_squeeze/__init__.py
bert_squeeze/assistants/__init__.py
bert_squeeze/assistants/configs/distil.yaml
bert_squeeze/assistants/configs/distil_hard.yaml
bert_squeeze/assistants/configs/distil_parallel.yaml
bert_squeeze/assistants/configs/distil_soft.yaml
bert_squeeze/assistants/configs/train_bert.yaml
bert_squeeze/assistants/configs/train_deebert.yaml
bert_squeeze/assistants/configs/train_fastbert.yaml
bert_squeeze/assistants/configs/train_lr.yaml
bert_squeeze/assistants/configs/train_lstm.yaml
bert_squeeze/assistants/configs/train_theseus_bert.yaml
bert_squeeze/assistants/distil_assistant.py
bert_squeeze/assistants/train_assistant.py
bert_squeeze/data/__init__.py
bert_squeeze/data/local_datasets/__init__.py
bert_squeeze/data/local_datasets/conference_dataset.py
bert_squeeze/data/local_datasets/parallel_dataset.py
bert_squeeze/data/local_datasets/unlabeled_dataset.py
bert_squeeze/data/modules/__init__.py
bert_squeeze/data/modules/distillation_module.py
bert_squeeze/data/modules/lr_module.py
bert_squeeze/data/modules/lstm_module.py
bert_squeeze/data/modules/transformer_module.py
bert_squeeze/distillation/__init__.py
bert_squeeze/distillation/distiller.py
bert_squeeze/distillation/utils/__init__.py
bert_squeeze/distillation/utils/labeler.py
bert_squeeze/inference/__init__.py
bert_squeeze/inference/model.py
bert_squeeze/inference/processors.py
bert_squeeze/models/__init__.py
bert_squeeze/models/base_lt_module.py
bert_squeeze/models/custom_transformers/__init__.py
bert_squeeze/models/custom_transformers/bert.py
bert_squeeze/models/custom_transformers/deebert.py
bert_squeeze/models/custom_transformers/fastbert.py
bert_squeeze/models/custom_transformers/theseus_bert.py
bert_squeeze/models/layers/__init__.py
bert_squeeze/models/layers/classifier.py
bert_squeeze/models/layers/mha.py
bert_squeeze/models/lr.py
bert_squeeze/models/lstm.py
bert_squeeze/models/lt_bert.py
bert_squeeze/models/lt_deebert.py
bert_squeeze/models/lt_distilbert.py
bert_squeeze/models/lt_fastbert.py
bert_squeeze-0.1.1.dist-info/METADATA
bert_squeeze-0.1.1.dist-info/WHEEL
bert_squeeze-0.1.1.dist-info/RECORD
