Metadata-Version: 2.1
Name: bert-squeeze
Version: 0.1.1
Summary: Tools for Transformers compression using PyTorch Lightning
Keywords: nlp,transformers,bert
Author: JulesBelveze
Author-email: jules.belveze@hotmail.fr
Requires-Python: >=3.8.1,<4.0
Classifier: Programming Language :: Python :: 3
Classifier: Programming Language :: Python :: 3.9
Classifier: Programming Language :: Python :: 3.10
Classifier: Programming Language :: Python :: 3.11
Classifier: Topic :: Scientific/Engineering :: Artificial Intelligence
Classifier: Topic :: Text Processing
Requires-Dist: datasets (>=1.8.0,<2.0.0)
Requires-Dist: huggingface-hub (==0.13.4)
Requires-Dist: hydra-core (>=1.1.1,<2.0.0)
Requires-Dist: lightning (>=2.0.0,<3.0.0)
Requires-Dist: matplotlib (<3.7.1)
Requires-Dist: neptune-client[pytorch-lightning] (>=0.14.0,<0.15.0)
Requires-Dist: numpy (<1.20.0)
Requires-Dist: omegaconf (>=2.1.0,<3.0.0)
Requires-Dist: overrides (>=6.1.0,<7.0.0)
Requires-Dist: psutil (>=5.8.0,<6.0.0)
Requires-Dist: python-dotenv (>=0.18.0,<0.19.0)
Requires-Dist: scikit-learn (>=1.2.2,<2.0.0)
Requires-Dist: seaborn (>=0.12.2,<0.13.0)
Requires-Dist: tabulate (>=0.8.9,<0.9.0)
Requires-Dist: torch (>=2.0.1,<3.0.0)
Requires-Dist: transformers (>=4.20.0,<5.0.0)
